scrcpy/__init__.py
scrcpy/const.py
scrcpy/control.py
scrcpy/core.py
my_scrcpy-0.3.dist-info/METADATA
my_scrcpy-0.3.dist-info/WHEEL
my_scrcpy-0.3.dist-info/top_level.txt
my_scrcpy-0.3.dist-info/RECORD
