Metadata-Version: 2.1
Name: my_scrcpy
Version: 0.3
Summary: Screen copy android
Home-page: https://github.com/NamHV4/scrcpy_namhv4
Author: NamHV4
Author-email: namhoang2110@gmail.com
Classifier: Programming Language :: Python :: 3
Classifier: License :: OSI Approved :: MIT License
Classifier: Operating System :: OS Independent
Requires-Python: >=3.6
